CHANGES.rst
CONTRIBUTORS.rst
MANIFEST.in
README.rst
bootstrap.py
buildout.cfg
setup.py
cpskin/__init__.py
cpskin.diazotheme.dream.egg-info/PKG-INFO
cpskin.diazotheme.dream.egg-info/SOURCES.txt
cpskin.diazotheme.dream.egg-info/dependency_links.txt
cpskin.diazotheme.dream.egg-info/entry_points.txt
cpskin.diazotheme.dream.egg-info/namespace_packages.txt
cpskin.diazotheme.dream.egg-info/not-zip-safe
cpskin.diazotheme.dream.egg-info/requires.txt
cpskin.diazotheme.dream.egg-info/top_level.txt
cpskin/diazotheme/__init__.py
cpskin/diazotheme/dream/__init__.py
cpskin/diazotheme/dream/configure.zcml
cpskin/diazotheme/dream/preview.png
cpskin/diazotheme/dream/upgradehandlers.py
cpskin/diazotheme/dream/profiles/default/cssregistry.xml
cpskin/diazotheme/dream/profiles/default/jsregistry.xml
cpskin/diazotheme/dream/profiles/default/lessregistry.xml
cpskin/diazotheme/dream/profiles/default/metadata.xml
cpskin/diazotheme/dream/profiles/default/theme.xml
cpskin/diazotheme/dream/profiles/uninstall/cssregistry.xml
cpskin/diazotheme/dream/profiles/uninstall/jsregistry.xml
cpskin/diazotheme/dream/profiles/uninstall/lessregistry.xml
cpskin/diazotheme/dream/static/manifest.cfg
cpskin/diazotheme/dream/static/preview.png
cpskin/diazotheme/dream/static/rules.xml
cpskin/diazotheme/dream/static/css/mobile-dream.css
cpskin/diazotheme/dream/static/css/styles.css
cpskin/diazotheme/dream/static/fragments/search.pt
cpskin/diazotheme/dream/static/images/cd-top-arrow.svg
cpskin/diazotheme/dream/static/js/movetotop.js
cpskin/diazotheme/dream/static/js/slidetoggle-search.js
cpskin/diazotheme/dream/static/js/sticky-navigation.js
cpskin/diazotheme/dream/static/less/mobile.less
cpskin/diazotheme/dream/static/less/mobilelarge.less
cpskin/diazotheme/dream/static/less/mobilemedium.less
cpskin/diazotheme/dream/static/less/styles.less
cpskin/diazotheme/dream/static/less/variables.less
cpskin/diazotheme/dream/static/overrides/plone.app.multilingual.browser.templates.languageselector.pt
cpskin/diazotheme/dream/static/rules/footer.xml
cpskin/diazotheme/dream/static/rules/header.xml
cpskin/diazotheme/dream/static/rules/portlets.xml
cpskin/diazotheme/dream/static/rules/structures.xml
docs/LICENSE.GPL
docs/LICENSE.rst