Metadata-Version: 1.1
Name: cpskin.diazotheme.dream
Version: 0.2.15
Summary: Dream Topnav
Home-page: https://github.com/IMIO/cpskin.diazotheme.dream/
Author: IMIO
Author-email: support@imio.be
License: GPL
Keywords: imio cpskin theme
Platform: UNKNOWN
Classifier: Environment :: Web Environment
Classifier: Framework :: Plone
Classifier: Framework :: Plone :: 4.3
Classifier: Programming Language :: Python
Classifier: Programming Language :: Python :: 2.7
